steamwebapi/__init__.py
steamwebapi/api.py
steamwebapi/printfunction.py
steamwebapi/profiles.py
steamwebapi/user.py
steamwebapi/utils.py
steamwebapi-0.1.3.dist-info/DESCRIPTION.rst
steamwebapi-0.1.3.dist-info/METADATA
steamwebapi-0.1.3.dist-info/RECORD
steamwebapi-0.1.3.dist-info/WHEEL
steamwebapi-0.1.3.dist-info/metadata.json
steamwebapi-0.1.3.dist-info/top_level.txt
