Metadata-Version: 1.1
Name: steamwebapi
Version: 0.1.3
Summary: Steam API Wrapper
Home-page: https://github.com/shawnsilva/steamwebapi
Author: Shawn Silva
Author-email: ssilva@jatgam.com
License: GNU GPL v3
Keywords: steam valve api web user group profile
Platform: Unix
Platform: Windows
Classifier: Development Status :: 4 - Beta
Classifier: Intended Audience :: Developers
Classifier: License :: OSI Approved :: GNU General Public License v3 (GPLv3)
Classifier: Programming Language :: Python :: 2
Classifier: Programming Language :: Python :: 2.6
Classifier: Programming Language :: Python :: 2.7
Classifier: Programming Language :: Python :: 3
Classifier: Programming Language :: Python :: 3.2
Classifier: Programming Language :: Python :: 3.3
Classifier: Programming Language :: Python :: 3.4
Classifier: Programming Language :: Python :: 3.5
Classifier: Natural Language :: English
Classifier: Operating System :: OS Independent
Classifier: Topic :: Internet
